huaweicloudsdkvpn/__init__.py
huaweicloudsdkvpn/v5/__init__.py
huaweicloudsdkvpn/v5/vpn_async_client.py
huaweicloudsdkvpn/v5/vpn_client.py
huaweicloudsdkvpn/v5/model/__init__.py
huaweicloudsdkvpn/v5/model/add_vpn_user_to_group_request_body.py
huaweicloudsdkvpn/v5/model/add_vpn_users_to_group_request.py
huaweicloudsdkvpn/v5/model/add_vpn_users_to_group_response.py
huaweicloudsdkvpn/v5/model/availability_zones.py
huaweicloudsdkvpn/v5/model/available_spec.py
huaweicloudsdkvpn/v5/model/batch_create_resource_tags_request.py
huaweicloudsdkvpn/v5/model/batch_create_resource_tags_response.py
huaweicloudsdkvpn/v5/model/batch_create_vpn_connection_request.py
huaweicloudsdkvpn/v5/model/batch_create_vpn_connection_request_body.py
huaweicloudsdkvpn/v5/model/batch_create_vpn_connection_response.py
huaweicloudsdkvpn/v5/model/batch_create_vpn_users_request.py
huaweicloudsdkvpn/v5/model/batch_create_vpn_users_request_body.py
huaweicloudsdkvpn/v5/model/batch_create_vpn_users_response.py
huaweicloudsdkvpn/v5/model/batch_delete_resource_tags_request.py
huaweicloudsdkvpn/v5/model/batch_delete_resource_tags_response.py
huaweicloudsdkvpn/v5/model/batch_delete_vpn_users_request.py
huaweicloudsdkvpn/v5/model/batch_delete_vpn_users_request_body.py
huaweicloudsdkvpn/v5/model/batch_delete_vpn_users_response.py
huaweicloudsdkvpn/v5/model/bgp_peer.py
huaweicloudsdkvpn/v5/model/ca_certificate.py
huaweicloudsdkvpn/v5/model/ca_certificate_request.py
huaweicloudsdkvpn/v5/model/check_client_ca_certificate_request.py
huaweicloudsdkvpn/v5/model/check_client_ca_certificate_response.py
huaweicloudsdkvpn/v5/model/connection.py
huaweicloudsdkvpn/v5/model/connection_monitor_info.py
huaweicloudsdkvpn/v5/model/connections_log_config.py
huaweicloudsdkvpn/v5/model/count_resources_by_tags_request.py
huaweicloudsdkvpn/v5/model/count_resources_by_tags_response.py
huaweicloudsdkvpn/v5/model/create_cgw_request.py
huaweicloudsdkvpn/v5/model/create_cgw_request_body.py
huaweicloudsdkvpn-3.1.184.dist-info/METADATA
huaweicloudsdkvpn-3.1.184.dist-info/WHEEL
huaweicloudsdkvpn-3.1.184.dist-info/licenses/LICENSE
huaweicloudsdkvpn-3.1.184.dist-info/RECORD
